eyefootball/__init__.py
eyefootball/command.py
eyefootball/rss.py
eyefootball-0.0.1.dist-info/METADATA
eyefootball-0.0.1.dist-info/WHEEL
eyefootball-0.0.1.dist-info/top_level.txt
eyefootball-0.0.1.dist-info/RECORD
