Metadata-Version: 2.1
Name: eyefootball
Version: 0.0.1
Summary: Link adapter for eyefootball.com rss service
Home-page: https://github.com/slvler/eyefootball
Author: slvler
Author-email: slvler@proton.me
Classifier: Programming Language :: Python :: 3
Classifier: License :: OSI Approved :: MIT License
Classifier: Operating System :: OS Independent
Requires-Python: >=3.9.6
Requires-Dist: feedparser (>=6.0.0)
Requires-Dist: future (>=0.18.3)
Requires-Dist: pywebview (>=4.0.1)
